{"edges": [[0, 1], [1, 2], [3, 4], [4, 5], [0, 6], [6, 7], [8, 9], [0, 10], [10, 11], [12, 13], [14, 15], [15, 16], [17, 18], [19, 20], [21, 22], [23, 24], [16, 25], [23, 25], [25, 26], [26, 27], [28, 29], [27, 30], [19, 31], [0, 33], [32, 33], [12, 34], [33, 34], [3, 35], [32, 35], [6, 36], [8, 36], [35, 36], [3, 37], [3, 38], [21, 39], [34, 39], [8, 40], [17, 40], [37, 40], [37, 41], [10, 42], [12, 42], [19, 42], [41, 43], [14, 44], [17, 44], [43, 44], [21, 45], [28, 45], [14, 46], [23, 46], [16, 47], [45, 48], [28, 49], [48, 50], [49, 51], [50, 51], [27, 52], [52, 53], [52, 54], [54, 55]], "features": {"0": "3", "1": "1", "2": "3", "3": "3", "4": "1", "5": "3", "6": "3", "7": "1", "8": "3", "9": "1", "10": "3", "11": "1", "12": "3", "13": "1", "14": "3", "15": "1", "16": "3", "17": "3", "18": "1", "19": "3", "20": "1", "21": "3", "22": "1", "23": "3", "24": "1", "25": "3", "26": "1", "27": "3", "28": "3", "29": "1", "30": "1", "31": "2", "32": "3", "33": "3", "34": "3", "35": "3", "36": "3", "37": "3", "38": "3", "39": "3", "40": "3", "41": "3", "42": "3", "43": "3", "44": "3", "45": "3", "46": "3", "47": "3", "48": "3", "49": "3", "50": "3", "51": "3", "52": "3", "53": "3", "54": "3", "55": "3"}}