{"edges": [[0, 1], [2, 3], [3, 4], [2, 5], [5, 6], [5, 7], [7, 8], [4, 9], [7, 9], [9, 10], [11, 12], [4, 13], [13, 14], [0, 15], [2, 15], [15, 16], [17, 18], [16, 19], [19, 20], [11, 21], [20, 21], [20, 22], [20, 23], [11, 24], [16, 24], [24, 25], [0, 26], [17, 26], [25, 26], [25, 27], [27, 28], [27, 29], [28, 30], [29, 31], [30, 32], [31, 32], [32, 33]], "features": {"0": "3", "1": "4", "2": "3", "3": "1", "4": "3", "5": "3", "6": "1", "7": "3", "8": "1", "9": "3", "10": "1", "11": "3", "12": "1", "13": "3", "14": "1", "15": "2", "16": "3", "17": "3", "18": "2", "19": "3", "20": "3", "21": "3", "22": "3", "23": "3", "24": "3", "25": "3", "26": "3", "27": "3", "28": "3", "29": "3", "30": "3", "31": "3", "32": "3", "33": "3"}}